scratch_sync/__init__.py
scratch_sync/__main__.py
scratch_sync/cli.py
scratch_sync/discovery.py
scratch_sync/syncthing.py
scratch_sync/tailscale.py
scratch_sync/uv.py
scratch_sync-0.2.0.dist-info/METADATA
scratch_sync-0.2.0.dist-info/WHEEL
scratch_sync-0.2.0.dist-info/entry_points.txt
scratch_sync-0.2.0.dist-info/RECORD
