Metadata-Version: 2.4
Name: scratch-sync
Version: 0.2.0
Summary: Sync private scratch/ folders across machines using Syncthing over Tailscale
Project-URL: Homepage, https://scratch.tlab.sh
Project-URL: Documentation, https://scratch.tlab.sh
Project-URL: Repository, https://github.com/talmolab/scratch-sync
Project-URL: Issues, https://github.com/talmolab/scratch-sync/issues
Author-email: Talmo Pereira <talmo@salk.edu>
License-Expression: MIT
Keywords: file-sync,peer-to-peer,scratch,sync,syncthing,tailscale
Classifier: Development Status :: 4 - Beta
Classifier: Environment :: Console
Classifier: Intended Audience :: Developers
Classifier: License :: OSI Approved :: MIT License
Classifier: Operating System :: OS Independent
Classifier: Programming Language :: Python :: 3
Classifier: Programming Language :: Python :: 3.10
Classifier: Programming Language :: Python :: 3.11
Classifier: Programming Language :: Python :: 3.12
Classifier: Programming Language :: Python :: 3.13
Classifier: Topic :: System :: Filesystems
Classifier: Topic :: Utilities
Requires-Python: >=3.10
Requires-Dist: click>=8.0
Requires-Dist: httpx>=0.25
Requires-Dist: questionary>=2.1
Requires-Dist: rich-click>=1.8
